hocker/HOCRCombiner.py
hocker/__init__.py
hocker-1.0.4.dist-info/METADATA
hocker-1.0.4.dist-info/WHEEL
hocker-1.0.4.dist-info/license_files/LICENSE
hocker-1.0.4.dist-info/RECORD
