Metadata-Version: 2.1
Name: hocker
Version: 1.0.4
Summary: Python package for combining .hocr files and images into searchable PDFs
Project-URL: Homepage, https://github.com/lucaswarwick02/HOCkeR
Project-URL: Bug Tracker, https://github.com/lucaswarwick02/HOCkeR/issues
Author-email: Lucas Warwick <lucaswarwick02@gmail.com>
License: MIT License
Classifier: License :: OSI Approved :: MIT License
Classifier: Operating System :: OS Independent
Classifier: Programming Language :: Python :: 3
Requires-Python: >=3.7
